bw2regional/__init__.py
bw2regional/base_data.py
bw2regional/databases.py
bw2regional/density.py
bw2regional/errors.py
bw2regional/geojson_export.py
bw2regional/hashing.py
bw2regional/intersection.py
bw2regional/loading.py
bw2regional/meta.py
bw2regional/pandarus.py
bw2regional/pandarus_remote.py
bw2regional/tests.py
bw2regional/topography.py
bw2regional/utils.py
bw2regional/validate.py
bw2regional/xtables.py
bw2regional/lca/__init__.py
bw2regional/lca/base_class.py
bw2regional/lca/extension_tables.py
bw2regional/lca/one_spatial_scale.py
bw2regional/lca/topo_extension_tables.py
bw2regional/lca/two_spatial_scales.py
bw2regional/lca/two_spatial_scales_weighting.py
bw2regional-0.5.2.dist-info/LICENSE.txt
bw2regional-0.5.2.dist-info/METADATA
bw2regional-0.5.2.dist-info/WHEEL
bw2regional-0.5.2.dist-info/top_level.txt
bw2regional-0.5.2.dist-info/RECORD
