Metadata-Version: 2.1
Name: bw2regional
Version: 0.5.2
Summary: UNKNOWN
Home-page: https://bitbucket.org/cmutel/brightway2-regional
Author: Chris Mutel
Author-email: cmutel@gmail.com
License: Copyright (c) 2014, Chris Mutel and ETH Zurich.
Requires-Dist: brightway2
Requires-Dist: bw2calc (>=1.2)
Requires-Dist: bw2data (>=2.0)
Requires-Dist: constructive-geometries
Requires-Dist: eight
Requires-Dist: fiona
Requires-Dist: pandas
Requires-Dist: pandarus (>=1.0)
Requires-Dist: requests
Requires-Dist: rower
Requires-Dist: stats-arrays
Requires-Dist: voluptuous
Requires-Dist: wrapt
